credmark/__init__.py
credmark/api/__init__.py
credmark/api/defi_api/__init__.py
credmark/api/defi_api/get_cached_model_results.py
credmark/api/defi_api/get_model_by_slug.py
credmark/api/defi_api/get_model_deployments_by_slug.py
credmark/api/defi_api/get_model_runtime_stats.py
credmark/api/defi_api/list_models.py
credmark/api/defi_api/run_model.py
credmark/api/misc/__init__.py
credmark/api/misc/check_health.py
credmark/api/misc/get_daily_model_usage.py
credmark/api/misc/get_top_models.py
credmark/api/misc/get_total_model_usage.py
credmark/api/portfolio_api/__init__.py
credmark/api/portfolio_api/get_positions.py
credmark/api/portfolio_api/get_positions_historical.py
credmark/api/portfolio_api/get_returns.py
credmark/api/portfolio_api/get_value.py
credmark/api/portfolio_api/get_value_historical.py
credmark/api/token_api/__init__.py
credmark/api/token_api/get_token_abi.py
credmark/api/token_api/get_token_balance.py
credmark/api/token_api/get_token_balance_historical.py
credmark/api/token_api/get_token_creation_block.py
credmark/api/token_api/get_token_decimals.py
credmark/api/token_api/get_token_holders.py
credmark/api/token_api/get_token_holders_count.py
credmark/api/token_api/get_token_holders_count_historical.py
credmark/api/token_api/get_token_logo.py
credmark/api/token_api/get_token_metadata.py
credmark/api/token_api/get_token_name.py
credmark/api/token_api/get_token_price.py
credmark/api/token_api/get_token_price_historical.py
credmark/api/token_api/get_token_symbol.py
credmark/api/token_api/get_token_total_supply.py
credmark/api/token_api/get_token_total_supply_historical.py
credmark/api/token_api/get_token_volume.py
credmark/api/token_api/get_token_volume_historical.py
credmark/api/utilities_api/__init__.py
credmark/api/utilities_api/block_from_timestamp.py
credmark/api/utilities_api/block_to_timestamp.py
credmark/api/utilities_api/cross_chain_block.py
credmark/api/utilities_api/get_chains.py
credmark/api/utilities_api/get_latest_block.py
credmark/client.py
credmark-1.5.0.dist-info/METADATA
credmark-1.5.0.dist-info/WHEEL
credmark-1.5.0.dist-info/RECORD
