Metadata-Version: 2.1
Name: credmark
Version: 1.5.0
Summary: A client library for accessing Credmark Gateway
Home-page: https://credmark.com
License: MIT
Author: Credmark
Author-email: info@credmark.com
Requires-Python: >=3.7,<4.0
Classifier: License :: OSI Approved :: MIT License
Classifier: Programming Language :: Python :: 3
Classifier: Programming Language :: Python :: 3.7
Classifier: Programming Language :: Python :: 3.8
Classifier: Programming Language :: Python :: 3.9
Classifier: Programming Language :: Python :: 3.10
Classifier: Programming Language :: Python :: 3.11
Requires-Dist: attrs (>=21.3.0)
Requires-Dist: httpx (>=0.15.4,<0.24.0)
Requires-Dist: python-dateutil (>=2.8.0,<3.0.0)
Project-URL: Documentation, https://docs.credmark.com/technical-docs
Project-URL: Repository, https://github.com/credmark/credmark-sdk-py
